remoteexec/__init__.py
remoteexec/exceptions.py
remoteexec/remoteexec.py
remoteexec/runnerfeature.py
remoteexec/communicate/__init__.py
remoteexec/communicate/communicator.py
remoteexec/communicate/exceptions.py
remoteexec/communicate/serializer.py
remoteexec/communicate/sync.py
remoteexec/hooks/__init__.py
remoteexec/hooks/hookbase.py
remoteexec/hooks/loophook.py
remoteexec/hooks/stephook.py
remoteexec/inout/__init__.py
remoteexec/inout/inout.py
pyremoteexec-1.0.1.dist-info/LICENSE
pyremoteexec-1.0.1.dist-info/METADATA
pyremoteexec-1.0.1.dist-info/WHEEL
pyremoteexec-1.0.1.dist-info/top_level.txt
pyremoteexec-1.0.1.dist-info/RECORD
