Metadata-Version: 2.1
Name: pyremoteexec
Version: 1.0.1
Summary: Python Remote Executer
Author: Toshiyuki Sakamoto
Author-email: toshiyuki.sakamoto@reiwa-ai.co.jp
Maintainer: Reiwa AI K.K.
Maintainer-email: contact@reiwa-ai.biz
License: MIT
Project-URL: homepage, https://www.reiwa-ai.co.jp/snippetbox.html
Project-URL: repository, https://github.com/reiwa-ai/python-remoteexec
Project-URL: documentation, https://reiwa-ai.github.io/python-remoteexec/
Classifier: Programming Language :: Python :: 3
Classifier: Programming Language :: Python :: 3.3
Classifier: Programming Language :: Python :: 3.4
Classifier: Programming Language :: Python :: 3.5
Classifier: Programming Language :: Python :: 3.6
Classifier: Programming Language :: Python :: 3.7
Classifier: Programming Language :: Python :: 3.8
Classifier: Programming Language :: Python :: 3.9
Classifier: Programming Language :: Python :: 3.10
Classifier: Programming Language :: Python :: 3.11
Classifier: License :: OSI Approved :: MIT License
License-File: LICENSE
